{
  "uuid": "e944c919-7ae9-4737-8033-ac073a1b8a90",
  "shortName": "Wizard",
  "longName": "Wizard",
  "companyName": "Stefen Friesen",
  "versionCode": 1,
  "versionLabel": "1.1",
  "watchapp": {
    "watchface": false
  },
  "appKeys": {
    "dummy": 0
  },
  "resources": {
    "media": [
      {
        "type": "raw",
        "name": "LOCALE_ENGLISH",
        "file": "locales/locale_english.bin"
      },
      {
        "type": "raw",
        "name": "LOCALE_FRENCH",
        "file": "locales/locale_french.bin"
      },
      {
        "type": "raw",
        "name": "LOCALE_SPANISH",
        "file": "locales/locale_spanish.bin"
      },
      {
        "type": "raw",
        "name": "LOCALE_GERMAN",
        "file": "locales/locale_german.bin"
      },
      {
        "type": "font",
        "characterRegex": "[:0-9]",
        "name": "FONT_SQUARE_48",
        "file": "fonts/square.ttf"
      },
      {
        "type": "png",
        "name": "IMAGE_ICON_SIRI",
        "file": "images/siri.png"
      },
      {
        "type": "png",
        "name": "IMAGE_ICON_REFRESH",
        "file": "images/refresh.png"
      },
      {
        "type": "png",
        "name": "IMAGE_ICON_ACTIVATOR",
        "file": "images/activator.png"
      },
      {
        "type": "png",
        "name": "IMAGE_ICON_DISCONNECTED",
        "file": "images/disconnected.png"
      },
      {
        "type": "png",
        "name": "IMAGE_ICON_PLAY_PAUSE",
        "file": "images/play_pause.png"
      },
      {
        "type": "png",
        "name": "IMAGE_ICON_NEXT",
        "file": "images/next.png"
      },
      {
        "type": "png",
        "name": "IMAGE_ICON_PREVIOUS",
        "file": "images/previous.png"
      },
      {
        "type": "png",
        "name": "IMAGE_BACKGROUND",
        "file": "images/background.png"
      },
      {
        "menuIcon": true,
        "type": "png",
        "name": "IMAGE_MENU_ICON",
        "file": "images/app_icon.png"
      }
    ]
  }
}
